drain/__init__.py
drain/aggregate.py
drain/aggregation.py
drain/data.py
drain/dedupe.py
drain/drake.py
drain/exploration.py
drain/metrics.py
drain/model.py
drain/serialize.py
drain/step.py
drain/util.py
drain-0.0.6.data/scripts/drain
drain-0.0.6.data/scripts/drake
drain-0.0.6.data/scripts/run_step.py
drain-0.0.6.data/scripts/to_drakefile.py
drain-0.0.6.dist-info/DESCRIPTION.rst
drain-0.0.6.dist-info/METADATA
drain-0.0.6.dist-info/RECORD
drain-0.0.6.dist-info/WHEEL
drain-0.0.6.dist-info/metadata.json
drain-0.0.6.dist-info/top_level.txt
