Metadata-Version: 2.0
Name: drain
Version: 0.0.6
Summary: pipeline library
Home-page: https://github.com/potash/drain
Author: Eric Potash
Author-email: epotash@uchicago.edu
License: MIT license
Keywords: drain
Platform: UNKNOWN
Classifier: Development Status :: 2 - Pre-Alpha
Classifier: Intended Audience :: Developers
Classifier: License :: OSI Approved :: MIT License
Classifier: Natural Language :: English
Classifier: Programming Language :: Python :: 2.7
Classifier: Programming Language :: Python :: 3.5
Requires-Dist: PyYAML
Requires-Dist: cached-property
Requires-Dist: repoze.lru
Requires-Dist: sqlalchemy
Requires-Dist: psycopg2
Requires-Dist: tables
Requires-Dist: pandas
Requires-Dist: numpy
Requires-Dist: scipy
Requires-Dist: joblib
Requires-Dist: six
Requires-Dist: sklearn
